lgl_get_ena_metafile/__init__.py
lgl_get_ena_metafile-3.0.dist-info/LICENSE
lgl_get_ena_metafile-3.0.dist-info/METADATA
lgl_get_ena_metafile-3.0.dist-info/WHEEL
lgl_get_ena_metafile-3.0.dist-info/top_level.txt
lgl_get_ena_metafile-3.0.dist-info/RECORD
