Metadata-Version: 2.1
Name: lgl-get-ena-metafile
Version: 3.0
Summary: ENA数据库高通量数据元数据(.txt)批量下载器
Home-page: UNKNOWN
Author: liugeliang
Author-email: sx_liugeliang@163.com
License: UNKNOWN
Platform: UNKNOWN
Classifier: Programming Language :: Python :: 3
Classifier: License :: OSI Approved :: MIT License
Classifier: Operating System :: OS Independent
Requires-Python: >=3.6
License-File: LICENSE
Requires-Dist: selenium
